pponnxcr/__init__.py
pponnxcr/log.py
pponnxcr/predict_system.py
pponnxcr/utility.py
pponnxcr/cls/__init__.py
pponnxcr/cls/postprocess.py
pponnxcr/cls/predict_cls.py
pponnxcr/det/__init__.py
pponnxcr/det/postprocess.py
pponnxcr/det/predict_det.py
pponnxcr/det/preprocess.py
pponnxcr/model/Multilingual_PP-OCRv3_det_infer.onnx
pponnxcr/model/ch_PP-OCRv3_det_infer.onnx
pponnxcr/model/ch_PP-OCRv3_rec_infer.onnx
pponnxcr/model/ch_ppocr_mobile_v2.0_cls_infer.onnx
pponnxcr/model/chinese_cht_PP-OCRv3_rec_infer.onnx
pponnxcr/model/chinese_cht_dict.txt
pponnxcr/model/en_PP-OCRv3_det_infer.onnx
pponnxcr/model/en_PP-OCRv3_rec_infer.onnx
pponnxcr/model/en_dict.txt
pponnxcr/model/japan_PP-OCRv3_rec_infer.onnx
pponnxcr/model/japan_dict.txt
pponnxcr/model/ppocr_keys_v1.txt
pponnxcr/rec/__init__.py
pponnxcr/rec/predict_rec.py
pponnxcr/rec/rec_decoder.py
pponnxcr-2.1.dist-info/LICENSE
pponnxcr-2.1.dist-info/METADATA
pponnxcr-2.1.dist-info/WHEEL
pponnxcr-2.1.dist-info/top_level.txt
pponnxcr-2.1.dist-info/RECORD
