Metadata-Version: 2.1
Name: pponnxcr
Version: 2.1
Summary: OCR based on onnxruntime with PaddleOCR models
Home-page: https://github.com/hgjazhgj/pponnxcr
Author: hgjazhgj
Author-email: hgjazhgj.jp@gmail.com
License: GNU AGPLv3
Platform: UNKNOWN
Classifier: Development Status :: 4 - Beta
Classifier: Operating System :: OS Independent
Classifier: Intended Audience :: Developers
Classifier: License :: OSI Approved :: GNU Affero General Public License v3
Classifier: Programming Language :: Python :: 3
Classifier: Topic :: Scientific/Engineering :: Image Recognition
Classifier: Topic :: Scientific/Engineering :: Artificial Intelligence
License-File: LICENSE
Requires-Dist: onnxruntime
Requires-Dist: numpy
Requires-Dist: opencv-python
Requires-Dist: shapely
Requires-Dist: pyclipper
